mybank/__init__.py
mybank/account.py
MYBANKPACKAGE-1.0.0.dist-info/METADATA
MYBANKPACKAGE-1.0.0.dist-info/WHEEL
MYBANKPACKAGE-1.0.0.dist-info/top_level.txt
MYBANKPACKAGE-1.0.0.dist-info/RECORD
