Metadata-Version: 2.1
Name: MYBANKPACKAGE
Version: 1.0.0
Summary: MyBank Inc. Banking System
Author: Sneha Iyer
Author-email: iyersneha243@gmail.com
